turbustat-1.3.dist-info/LICENSE
turbustat-1.3.dist-info/METADATA
turbustat-1.3.dist-info/RECORD
turbustat-1.3.dist-info/top_level.txt
turbustat-1.3.dist-info/WHEEL
turbustat/compiler_version.cpython-37m-x86_64-linux-gnu.so
turbustat/_astropy_init.py
turbustat/__init__.py
turbustat/conftest.py
turbustat/version.py
turbustat/simulator/make_cube.py
turbustat/simulator/__init__.py
turbustat/simulator/spectrum.cpython-37m-x86_64-linux-gnu.so
turbustat/simulator/gen_field.py
turbustat/simulator/threeD_pspec.py
turbustat/simulator/tests/test_extended_fields.py
turbustat/simulator/tests/__init__.py
turbustat/simulator/tests/test_ppv.py
turbustat/tests/test_input_type.py
turbustat/tests/test_load_beam.py
turbustat/tests/test_ellipplaw.py
turbustat/tests/setup_package.py
turbustat/tests/test_genus.py
turbustat/tests/test_mahalanobis.py
turbustat/tests/test_wavelet.py
turbustat/tests/test_scf.py
turbustat/tests/test_cramer.py
turbustat/tests/test_pca.py
turbustat/tests/test_mvc.py
turbustat/tests/test_basestatistic.py
turbustat/tests/test_lmseg.py
turbustat/tests/test_dendro.py
turbustat/tests/_testing_data.py
turbustat/tests/testing_utilities.py
turbustat/tests/test_delvar.py
turbustat/tests/test_bispec.py
turbustat/tests/helpers.py
turbustat/tests/test_rfft_to_fft.py
turbustat/tests/__init__.py
turbustat/tests/test_vcs.py
turbustat/tests/test_sim_tools.py
turbustat/tests/generate_test_images.py
turbustat/tests/test_pspec.py
turbustat/tests/test_tsallis.py
turbustat/tests/test_stat_moments.py
turbustat/tests/test_vca.py
turbustat/tests/test_pdf.py
turbustat/tests/data/header.fits
turbustat/tests/data/dataset1.npz
turbustat/tests/data/create_testing_sets.py
turbustat/tests/data/checkVals.npz
turbustat/tests/data/dataset2.npz
turbustat/tests/data/computed_distances.npz
turbustat/tests/data/GetVals.py
turbustat/io/try_load_beamwidth.py
turbustat/io/__init__.py
turbustat/io/input_base.py
turbustat/io/sim_tools.py
turbustat/statistics/base_statistic.py
turbustat/statistics/fitting_utils.py
turbustat/statistics/stats_utils.py
turbustat/statistics/apodizing_kernels.py
